mathgenproject/__init__.py
mathgenproject/items.py
mathgenproject/middlewares.py
mathgenproject/pipelines.py
mathgenproject/settings.py
mathgenproject/utils.py
mathgenproject/spiders/__init__.py
mathgenproject/spiders/math_gen_project_spider.py
mathgenproject_jgolden17-0.1.0.dist-info/LICENSE
mathgenproject_jgolden17-0.1.0.dist-info/METADATA
mathgenproject_jgolden17-0.1.0.dist-info/WHEEL
mathgenproject_jgolden17-0.1.0.dist-info/top_level.txt
mathgenproject_jgolden17-0.1.0.dist-info/RECORD
