Metadata-Version: 2.1
Name: mathgenproject-jgolden17
Version: 0.1.0
Summary: Mathematics Genealogy Project Spider
Home-page: https://github.com/jgolden17/mathgenproject
Author: Jonathan Golden
License: UNKNOWN
Platform: UNKNOWN
Classifier: Programming Language :: Python :: 3
Classifier: License :: OSI Approved :: MIT License
Classifier: Operating System :: OS Independent
Requires-Python: >=3.6
